np_gui/__init__.py
np_gui/alphabet/liberation_serif/line_0_char0.png
np_gui/alphabet/liberation_serif/line_0_char1.png
np_gui/alphabet/liberation_serif/line_0_char10.png
np_gui/alphabet/liberation_serif/line_0_char11.png
np_gui/alphabet/liberation_serif/line_0_char12.png
np_gui/alphabet/liberation_serif/line_0_char13.png
np_gui/alphabet/liberation_serif/line_0_char14.png
np_gui/alphabet/liberation_serif/line_0_char15.png
np_gui/alphabet/liberation_serif/line_0_char16.png
np_gui/alphabet/liberation_serif/line_0_char17.png
np_gui/alphabet/liberation_serif/line_0_char18.png
np_gui/alphabet/liberation_serif/line_0_char19.png
np_gui/alphabet/liberation_serif/line_0_char2.png
np_gui/alphabet/liberation_serif/line_0_char20.png
np_gui/alphabet/liberation_serif/line_0_char21.png
np_gui/alphabet/liberation_serif/line_0_char22.png
np_gui/alphabet/liberation_serif/line_0_char23.png
np_gui/alphabet/liberation_serif/line_0_char24.png
np_gui/alphabet/liberation_serif/line_0_char25.png
np_gui/alphabet/liberation_serif/line_0_char26.png
np_gui/alphabet/liberation_serif/line_0_char27.png
np_gui/alphabet/liberation_serif/line_0_char28.png
np_gui/alphabet/liberation_serif/line_0_char29.png
np_gui/alphabet/liberation_serif/line_0_char3.png
np_gui/alphabet/liberation_serif/line_0_char30.png
np_gui/alphabet/liberation_serif/line_0_char31.png
np_gui/alphabet/liberation_serif/line_0_char32.png
np_gui/alphabet/liberation_serif/line_0_char33.png
np_gui/alphabet/liberation_serif/line_0_char34.png
np_gui/alphabet/liberation_serif/line_0_char35.png
np_gui/alphabet/liberation_serif/line_0_char36.png
np_gui/alphabet/liberation_serif/line_0_char37.png
np_gui/alphabet/liberation_serif/line_0_char38.png
np_gui/alphabet/liberation_serif/line_0_char39.png
np_gui/alphabet/liberation_serif/line_0_char4.png
np_gui/alphabet/liberation_serif/line_0_char40.png
np_gui/alphabet/liberation_serif/line_0_char41.png
np_gui/alphabet/liberation_serif/line_0_char42.png
np_gui-0.1.0.dist-info/METADATA
np_gui-0.1.0.dist-info/WHEEL
np_gui-0.1.0.dist-info/RECORD
