Metadata-Version: 2.1
Name: np-gui
Version: 0.1.0
Summary: This package implements Graphical User Interfaces from a NumPy user perspective.
License: MIT
Author: Gaël Cousin
Author-email: gcousin333@gmail.com
Requires-Python: >=3.10.6,<4.0.0
Classifier: License :: OSI Approved :: MIT License
Classifier: Programming Language :: Python :: 3
Classifier: Programming Language :: Python :: 3.11
Requires-Dist: matplotlib (>=3.0.0,<4.0.0)
Requires-Dist: numpy (>=1.21.0,<2.0.0)
Requires-Dist: scikit-image (>=0.19.0,<0.20.0)
Requires-Dist: typeguard (>=3.0.0,<4.0.0)
